{
  "$schema": "http://json-schema.org/draft-06/schema#",
  "$ref": "#/definitions/Welcome1",
  "definitions": {
    "Welcome1": {
      "type": "object",
      "additionalProperties": false,
      "properties": {
        "team": {
          "$ref": "#/definitions/Team"
        }
      },
      "required": [
        "team"
      ],
      "title": "Welcome1"
    },
    "Team": {
      "type": "object",
      "additionalProperties": false,
      "properties": {
        "name": {
          "type": "string"
        },
        "slug": {
          "type": "string"
        },
        "shortName": {
          "type": "string"
        },
        "gender": {
          "type": "string"
        },
        "sport": {
          "$ref": "#/definitions/Sport"
        },
        "category": {
          "$ref": "#/definitions/Category"
        },
        "tournament": {
          "$ref": "#/definitions/Tournament"
        },
        "primaryUniqueTournament": {
          "$ref": "#/definitions/UniqueTournament"
        },
        "userCount": {
          "type": "integer"
        },
        "manager": {
          "$ref": "#/definitions/Manager"
        },
        "venue": {
          "$ref": "#/definitions/Venue"
        },
        "nameCode": {
          "type": "string"
        },
        "class": {
          "type": "integer"
        },
        "disabled": {
          "type": "boolean"
        },
        "national": {
          "type": "boolean"
        },
        "type": {
          "type": "integer"
        },
        "id": {
          "type": "integer"
        },
        "country": {
          "$ref": "#/definitions/Country"
        },
        "fullName": {
          "type": "string"
        },
        "teamColors": {
          "$ref": "#/definitions/TeamColors"
        },
        "foundationDateTimestamp": {
          "type": "integer"
        },
        "fieldTranslations": {
          "$ref": "#/definitions/TeamFieldTranslations"
        }
      },
      "required": [
        "category",
        "class",
        "country",
        "disabled",
        "fieldTranslations",
        "foundationDateTimestamp",
        "fullName",
        "gender",
        "id",
        "manager",
        "name",
        "nameCode",
        "national",
        "primaryUniqueTournament",
        "shortName",
        "slug",
        "sport",
        "teamColors",
        "tournament",
        "type",
        "userCount",
        "venue"
      ],
      "title": "Team"
    },
    "Category": {
      "type": "object",
      "additionalProperties": false,
      "properties": {
        "name": {
          "type": "string"
        },
        "slug": {
          "type": "string"
        },
        "sport": {
          "$ref": "#/definitions/Sport"
        },
        "id": {
          "type": "integer"
        },
        "country": {
          "$ref": "#/definitions/Country"
        },
        "flag": {
          "type": "string"
        },
        "alpha2": {
          "type": "string"
        }
      },
      "required": [
        "alpha2",
        "country",
        "flag",
        "id",
        "name",
        "slug",
        "sport"
      ],
      "title": "Category"
    },
    "Country": {
      "type": "object",
      "additionalProperties": false,
      "properties": {
        "alpha2": {
          "type": "string"
        },
        "alpha3": {
          "type": "string"
        },
        "name": {
          "type": "string"
        }
      },
      "required": [
        "alpha2",
        "alpha3",
        "name"
      ],
      "title": "Country"
    },
    "Sport": {
      "type": "object",
      "additionalProperties": false,
      "properties": {
        "name": {
          "type": "string"
        },
        "slug": {
          "type": "string"
        },
        "id": {
          "type": "integer"
        }
      },
      "required": [
        "id",
        "name",
        "slug"
      ],
      "title": "Sport"
    },
    "TeamFieldTranslations": {
      "type": "object",
      "additionalProperties": false,
      "properties": {
        "nameTranslation": {
          "$ref": "#/definitions/NameTranslation"
        },
        "shortNameTranslation": {
          "$ref": "#/definitions/ShortNameTranslation"
        }
      },
      "required": [
        "nameTranslation",
        "shortNameTranslation"
      ],
      "title": "TeamFieldTranslations"
    },
    "NameTranslation": {
      "type": "object",
      "additionalProperties": false,
      "properties": {
        "ar": {
          "type": "string"
        },
        "ru": {
          "type": "string"
        }
      },
      "required": [
        "ar",
        "ru"
      ],
      "title": "NameTranslation"
    },
    "ShortNameTranslation": {
      "type": "object",
      "additionalProperties": false,
      "title": "ShortNameTranslation"
    },
    "Manager": {
      "type": "object",
      "additionalProperties": false,
      "properties": {
        "name": {
          "type": "string"
        },
        "slug": {
          "type": "string"
        },
        "shortName": {
          "type": "string"
        },
        "id": {
          "type": "integer"
        },
        "country": {
          "$ref": "#/definitions/Country"
        },
        "fieldTranslations": {
          "$ref": "#/definitions/ManagerFieldTranslations"
        }
      },
      "required": [
        "country",
        "fieldTranslations",
        "id",
        "name",
        "shortName",
        "slug"
      ],
      "title": "Manager"
    },
    "ManagerFieldTranslations": {
      "type": "object",
      "additionalProperties": false,
      "properties": {
        "nameTranslation": {
          "$ref": "#/definitions/ShortNameTranslationClass"
        },
        "shortNameTranslation": {
          "$ref": "#/definitions/ShortNameTranslationClass"
        }
      },
      "required": [
        "nameTranslation",
        "shortNameTranslation"
      ],
      "title": "ManagerFieldTranslations"
    },
    "ShortNameTranslationClass": {
      "type": "object",
      "additionalProperties": false,
      "properties": {
        "ar": {
          "type": "string"
        }
      },
      "required": [
        "ar"
      ],
      "title": "ShortNameTranslationClass"
    },
    "UniqueTournament": {
      "type": "object",
      "additionalProperties": false,
      "properties": {
        "name": {
          "type": "string"
        },
        "slug": {
          "type": "string"
        },
        "primaryColorHex": {
          "type": "string"
        },
        "secondaryColorHex": {
          "type": "string"
        },
        "category": {
          "$ref": "#/definitions/Category"
        },
        "userCount": {
          "type": "integer"
        },
        "hasPerformanceGraphFeature": {
          "type": "boolean"
        },
        "id": {
          "type": "integer"
        },
        "country": {
          "$ref": "#/definitions/ShortNameTranslation"
        },
        "displayInverseHomeAwayTeams": {
          "type": "boolean"
        }
      },
      "required": [
        "category",
        "country",
        "displayInverseHomeAwayTeams",
        "hasPerformanceGraphFeature",
        "id",
        "name",
        "primaryColorHex",
        "secondaryColorHex",
        "slug",
        "userCount"
      ],
      "title": "UniqueTournament"
    },
    "TeamColors": {
      "type": "object",
      "additionalProperties": false,
      "properties": {
        "primary": {
          "type": "string"
        },
        "secondary": {
          "type": "string"
        },
        "text": {
          "type": "string"
        }
      },
      "required": [
        "primary",
        "secondary",
        "text"
      ],
      "title": "TeamColors"
    },
    "Tournament": {
      "type": "object",
      "additionalProperties": false,
      "properties": {
        "name": {
          "type": "string"
        },
        "slug": {
          "type": "string"
        },
        "category": {
          "$ref": "#/definitions/Category"
        },
        "uniqueTournament": {
          "$ref": "#/definitions/UniqueTournament"
        },
        "priority": {
          "type": "integer"
        },
        "isLive": {
          "type": "boolean"
        },
        "id": {
          "type": "integer"
        }
      },
      "required": [
        "category",
        "id",
        "isLive",
        "name",
        "priority",
        "slug",
        "uniqueTournament"
      ],
      "title": "Tournament"
    },
    "Venue": {
      "type": "object",
      "additionalProperties": false,
      "properties": {
        "city": {
          "$ref": "#/definitions/City"
        },
        "venueCoordinates": {
          "$ref": "#/definitions/VenueCoordinates"
        },
        "hidden": {
          "type": "boolean"
        },
        "slug": {
          "type": "string"
        },
        "name": {
          "type": "string"
        },
        "capacity": {
          "type": "integer"
        },
        "id": {
          "type": "integer"
        },
        "country": {
          "$ref": "#/definitions/Country"
        },
        "fieldTranslations": {
          "$ref": "#/definitions/VenueFieldTranslations"
        },
        "stadium": {
          "$ref": "#/definitions/Stadium"
        }
      },
      "required": [
        "capacity",
        "city",
        "country",
        "fieldTranslations",
        "hidden",
        "id",
        "name",
        "slug",
        "stadium",
        "venueCoordinates"
      ],
      "title": "Venue"
    },
    "City": {
      "type": "object",
      "additionalProperties": false,
      "properties": {
        "name": {
          "type": "string"
        }
      },
      "required": [
        "name"
      ],
      "title": "City"
    },
    "VenueFieldTranslations": {
      "type": "object",
      "additionalProperties": false,
      "properties": {
        "nameTranslation": {
          "$ref": "#/definitions/ShortNameTranslationClass"
        },
        "shortNameTranslation": {
          "$ref": "#/definitions/ShortNameTranslation"
        }
      },
      "required": [
        "nameTranslation",
        "shortNameTranslation"
      ],
      "title": "VenueFieldTranslations"
    },
    "Stadium": {
      "type": "object",
      "additionalProperties": false,
      "properties": {
        "name": {
          "type": "string"
        },
        "capacity": {
          "type": "integer"
        }
      },
      "required": [
        "capacity",
        "name"
      ],
      "title": "Stadium"
    },
    "VenueCoordinates": {
      "type": "object",
      "additionalProperties": false,
      "properties": {
        "latitude": {
          "type": "number"
        },
        "longitude": {
          "type": "number"
        }
      },
      "required": [
        "latitude",
        "longitude"
      ],
      "title": "VenueCoordinates"
    }
  }
}
